ensure/__init__.py
ensure/_types.py
ensure/main.py
ensure-1.0.4.dist-info/LICENSE
ensure-1.0.4.dist-info/METADATA
ensure-1.0.4.dist-info/WHEEL
ensure-1.0.4.dist-info/top_level.txt
ensure-1.0.4.dist-info/RECORD
