Metadata-Version: 2.1
Name: ensure
Version: 1.0.4
Summary: Literate BDD assertions in Python with no magic
Home-page: https://github.com/kislyuk/ensure
Author: Andrey Kislyuk
Author-email: kislyuk@gmail.com
License: Apache Software License
Platform: MacOS X
Platform: Posix
Classifier: Intended Audience :: Developers
Classifier: License :: OSI Approved :: Apache Software License
Classifier: Operating System :: MacOS :: MacOS X
Classifier: Operating System :: POSIX
Classifier: Programming Language :: Python
Classifier: Programming Language :: Python :: 3
Classifier: Programming Language :: Python :: 3.7
Classifier: Programming Language :: Python :: 3.8
Classifier: Programming Language :: Python :: 3.9
Classifier: Programming Language :: Python :: 3.10
Classifier: Programming Language :: Python :: 3.11
Classifier: Development Status :: 5 - Production/Stable
Classifier: Topic :: Software Development :: Libraries :: Python Modules
Requires-Python: >=3.6
License-File: LICENSE
Requires-Dist: six>=1.11.0
Provides-Extra: test
Requires-Dist: coverage; extra == "test"
Requires-Dist: ruff; extra == "test"
